clean_cmake_project/ProjectSkeleton.py
clean_cmake_project/__init__.py
clean_cmake_project-0.0.4.dist-info/LICENSE
clean_cmake_project-0.0.4.dist-info/METADATA
clean_cmake_project-0.0.4.dist-info/WHEEL
clean_cmake_project-0.0.4.dist-info/entry_points.txt
clean_cmake_project-0.0.4.dist-info/top_level.txt
clean_cmake_project-0.0.4.dist-info/RECORD
