Metadata-Version: 2.1
Name: clean-cmake-project
Version: 0.0.4
Summary: A script to build cmake project for c++ using python
Home-page: https://github.com/FrenchCommando/clean_cmake_project
Author: FrenchCommando
Author-email: martialren@gmail.com
License: UNKNOWN
Platform: UNKNOWN
Classifier: Programming Language :: Python :: 3.7
Classifier: License :: OSI Approved :: MIT License
Classifier: Operating System :: OS Independent
